MANIFEST.in
README.md
setup.py
docs/.DS_Store
docs/Makefile
docs/make.bat
docs/build/.DS_Store
docs/build/doctrees/decorators.doctree
docs/build/doctrees/environment.pickle
docs/build/doctrees/index.doctree
docs/build/doctrees/quick_start.doctree
docs/build/doctrees/api/server.doctree
docs/build/html/.DS_Store
docs/build/html/.buildinfo
docs/build/html/decorators.html
docs/build/html/genindex.html
docs/build/html/index.html
docs/build/html/objects.inv
docs/build/html/quick_start.html
docs/build/html/search.html
docs/build/html/searchindex.js
docs/build/html/_sources/decorators.txt
docs/build/html/_sources/index.txt
docs/build/html/_sources/quick_start.txt
docs/build/html/_sources/api/server.txt
docs/build/html/_static/ajax-loader.gif
docs/build/html/_static/basic.css
docs/build/html/_static/comment-bright.png
docs/build/html/_static/comment-close.png
docs/build/html/_static/comment.png
docs/build/html/_static/default.css
docs/build/html/_static/doctools.js
docs/build/html/_static/down-pressed.png
docs/build/html/_static/down.png
docs/build/html/_static/file.png
docs/build/html/_static/jquery.js
docs/build/html/_static/minus.png
docs/build/html/_static/nature.css
docs/build/html/_static/plus.png
docs/build/html/_static/pygments.css
docs/build/html/_static/searchtools.js
docs/build/html/_static/sidebar.js
docs/build/html/_static/underscore.js
docs/build/html/_static/up-pressed.png
docs/build/html/_static/up.png
docs/build/html/_static/websupport.js
docs/build/html/api/server.html
docs/source/conf.py
docs/source/decorators.rst
docs/source/index.rst
docs/source/quick_start.rst
docs/source/api/server.rst
tailor/__init__.py
tailor/decorators.py
tailor/keygen.py
tailor/models.py
tailor/stitch.py
tailor/test.py
tailor/urls.py
tailor/views.py
tailor.egg-info/PKG-INFO
tailor.egg-info/SOURCES.txt
tailor.egg-info/dependency_links.txt
tailor.egg-info/not-zip-safe
tailor.egg-info/top_level.txt