Metadata-Version: 1.0
Name: tailor
Version: 0.1dev
Summary: Web based Fabric Execution
Home-page: UNKNOWN
Author: Derek Stegelman, Garrett Pennington, Jon Faustman
Author-email: UNKNOWN
License: MIT
Platform: UNKNOWN
Classifier: Development Status :: 1 - Planning
Classifier: Environment :: Web Environment
Classifier: Intended Audience :: End Users/Desktop
Classifier: Natural Language :: English
Classifier: Operating System :: OS Independent
Classifier: Programming Language :: Python
Classifier: Topic :: Internet :: WWW/HTTP :: Dynamic Content :: CGI Tools/Libraries
Classifier: Topic :: Utilities
Classifier: License :: OSI Approved :: MIT License
